ASR_metrics/calculate.py
ASR_metrics/utils.py
ASR_metrics-1.0.12.dist-info/DESCRIPTION.rst
ASR_metrics-1.0.12.dist-info/METADATA
ASR_metrics-1.0.12.dist-info/RECORD
ASR_metrics-1.0.12.dist-info/WHEEL
ASR_metrics-1.0.12.dist-info/entry_points.txt
ASR_metrics-1.0.12.dist-info/metadata.json
ASR_metrics-1.0.12.dist-info/top_level.txt
